threadsecurity/__init__.py
threadsecurity-0.1.dist-info/METADATA
threadsecurity-0.1.dist-info/WHEEL
threadsecurity-0.1.dist-info/top_level.txt
threadsecurity-0.1.dist-info/RECORD
