Metadata-Version: 2.4
Name: threadsecurity
Version: 0.1
Summary: A fun CTF-style package with a hidden flag
Author: Vishal Kumar
Author-email: vishal@example.com
Requires-Python: >=3.6
Dynamic: author
Dynamic: author-email
Dynamic: requires-python
Dynamic: summary
